{
  "iso_code": "CZE",
  "country_kr": "체코",
  "country_en": "Czech Republic",
  "flag_image": "public/images/CZE.gif",
  "travel_alert": {
    "level": "없음",
    "national_level": "없음",
    "partial_level": null,
    "regions": []
  },
  "accident_info_html": "",
  "local_contact_html": "<div>\n<h3>대사관 연락처</h3> ㅇ 주소 : Pelleova 15, 160 00 Praha 6-Bubenec, Czech Republic<br>\nㅇ 대표번호(근무시간 중) : (420) 234-090-411 <br>\nㅇ 긴급연락처(사건사고 등 긴급상황 발생 시, 24시간) : (420) 725-352-420 <br>\nㅇ 이메일 : czech@mofa.go.kr<br>\nㅇ 영사콜센터(24시간) : +82-2-3210-0404<br>\n\n<p>※ (무료)스마트폰에 무료앱 설치 이용</p><br>\n\n<h3>주재국 신고</h3> [현지에서 전화 걸 때]<br>\nㅇ 통합긴급전화 핫라인 : 112 (영어 가능)<br>\nㅇ 경찰 : 158<br>\nㅇ 시경찰 : 156<br>\nㅇ 화재 : 150<br>\nㅇ 응급환자 : 155<br>\nㅇ 자동차고장 : 1230<br>\nㅇ 자동차사고 : 1240<br>\nㅇ 프라하 관광정보 센터 : 221-714-714<br>\n<br>\n [국내에서 전화 걸 때] <br>\nㅇ 국가번호 420을 누른 후 해당 번호를 누릅니다.<br>\n<br>\n\n<h3>의료기관 연락처</h3> [프라하 지역 영어 진료 가능병원]<br>\nㅇ Unicare Medical Center(한국어 상담도 가능)<br>\n\n<p>- 주소: Na Dlouhem lanu 11, Praha 6<br>\n- 홈페이지: <a href=\"http://www.unicare.cz/\" target=\"_blank\" rel=\"noopener\">www.unicare.cz</a><br>- 전화번호: +420 235-356-553(영어), +420 602-201-040(한국어)</p><br>\n ㅇ Nemocnice Na Motol<br>\n\n<p>- 주소: V uvalu 84, Praha 5<br>\n- 홈페이지: <a href=\"http://www.fnmotol.cz\" target=\"_blank\" rel=\"noopener\">www.fnmotol.cz</a><br>- 전화번호: +420 224-431-111</p><br>\n ㅇ Nemocnice Na Homolce<br>\n\n<p>- 주소: Roentgenova 37/2, 150 00, Praha 5<br>\n- 홈페이지: <a href=\"http://www.homolka.cz/\" target=\"_blank\" rel=\"noopener\">www.homolka.cz</a><br>- 전화번호: +420 257-271-111</p><br>\n ㅇ Prague Central Military Hospital<br>\n\n<p>- 주소: U Vojenske nemocnice 1200, Praha 6<br>\n- 홈페이지: <a href=\"http://www.uvn.cz\" target=\"_blank\" rel=\"noopener\">www.uvn.cz</a><br>- 전화번호: +420 973-208-333</p><br>\n ㅇ Canadian Medical Care<br>\n\n<p>- 주소: Evropska 859/115a, 160 00 Praha 6<br>\n- 홈페이지: <a href=\"http://www.cmcpraha.com\" target=\"_blank\" rel=\"noopener\">www.cmcpraha.com</a><br>- 전화번호: +420 235-360-133</p><br>\n ㅇ Dental Emergencies (American Dentist in Prague)<br>\n\n<p>- 주소: pstrossova 10, 110 00 Praha 1<br>\n- 홈페이지: <a href=\"http://www.americandentist.cz\" target=\"_blank\" rel=\"noopener\">www.americandentist.cz</a><br>- 전화번호: +420 773-505-773</p></div>",
  "notice_url": "https://www.0404.go.kr/ntnSafetyInfo/list",
  "culture_ai": {
    "etiquette": "💡 **현지 문화 및 예절**\n* **대중교통 이용**\n    * 노약자 및 임산부에게 **좌석 양보 필수**\n    * 열차와 트램 내 **정숙 유지**\n* **식당 및 팁 문화**\n    * 서비스 만족 시 총액의 **5~10% 정도 팁 권장**\n    * 물 값은 **별도 계산이 일반적**",
    "local_laws": "🚨 **필수 준수 사항 및 주의 법률**\n* **교통권 검표**\n    * 티켓 **사전 구매 및 펀칭 필수**\n    * 무임승차 적발 시 **고액의 벌금 부과**\n* **음주 및 노상**\n    * 지정된 장소 외 **공공장소 음주 금지**\n    * 공공기물 파손 시 **형사 처벌 가능**\n* **소매치기 주의**\n    * 프라하 구시가지 등 인파 밀집 지역 **소지품 분실 주의**",
    "phrases": [
      "안녕하세요 - 도브리 덴(Dobrý den)",
      "감사합니다 - 데쿠이(Děkuji)",
      "죄송합니다 - 프로심(Prosím)",
      "얼마인가요? - 콜릭 스토이? (Kolik stojí?)",
      "계산해 주세요 - 자플라팀(Zaplatím)"
    ]
  }
}