{
  "iso_code": "HUN",
  "country_kr": "헝가리",
  "country_en": "Hungary",
  "flag_image": "images/HUN.gif",
  "travel_alert": {
    "level": "없음",
    "regions": []
  },
  "accident_info_html": "<div><h3 class=\"tit\">사건ㆍ사고 현황</h3>\r\nㅇ 헝가리의 치안은 유럽에서 안정적이라는 평가를 받고 있어 외국인이 여행 중에 살인, 강도, 납치 등 신체 및 생명의 위협을 당하는 등 강력범죄 피해가 거의 없으나, 관광지나 외곽지역, 유흥가, 대중교통 이용시에는 소매치기와 소지품 분실을 조심해야 합니다.<br><br>\r\n\r\n<h3 class=\"tit\">사건ㆍ사고의 유형</h3>\r\n[사례]<br>\r\nㅇ 비엔나-부다페스트 행 나라간 이동 기차 내에서의 여권 및 소지품 분실 사고가 급증하고 있습니다.<br><br>\r\n\r\n[유형]<br>\r\nㅇ 부다페스트 도착 전, 중간 역에서 기차가 출발하기 직전 가방 등 귀중품을 들고 도주 하차<br>\r\nㅇ 열차 안에서 티켓 검사, 자리 확인, 승객 승․하차 (특히, 국경 근처 전·후 정거장) 등 소란한 틈을 이용한 소매치기<br><br>\r\n\r\n[대책]<br>\r\nㅇ 귀중한 소중품은 항상 신체 가까이 휴대하고 기차가 잠시 정차한 시에는 귀중품이 든 가방은 손에 쥐고 있는 것이 좋습니다.<br><br>\r\n\r\n[사례]<br>\r\nㅇ 헝가리 바찌(Vaci)거리 및 웨스트엔드(Westend) 쇼핑몰 등에 위치한 일부 화장품 매장(SEACRET 등)에서 외국인 여행객을 대상으로 결제 사기가 빈번히 발생하여 주의가 필요합니다.<br><br>\r\n\r\n[유형]<br>\r\nㅇ 화장품 매장 직원이 한국말로 접근, 젤리모양의 비누 등을 선물로 주며 매장을 구경하도록 호객 행위를 함.&nbsp;<br>\r\n<p style=\"margin-left: 15px; margin-right: 15px;\">- 매장 내 직원이 화장품을 소개 및 무료 서비스를 제공하며 구매를 유도하고 상품 결재 시 얘기한 판매 가격에 0 을 하나 더 붙이는 방식으로 결제 금액 사기</p>\r\n<br>\r\n<p style=\"margin-left: 15px; margin-right: 15px;\">- 구매자가 카드 결제 후 이 사실을 인지하여 환불을 요청시, 환불이 불가능하다고 일방적 환불 불가 안내</p><br>\r\n\r\n[대책]<br>\r\nㅇ 카드 결제 전 (Pin Code 입력 혹은 서명 전) 반드시 해당 구매가격 확인 후 결제<br>\r\nㅇ 해외에서 카드를 이용하여 가맹점에서 부당한 처리를 했을 경우 즉시 해당 카드사에 연락하여 해외이용 이의신청(해외조사접수)<br>\r\n<p style=\"margin-left: 15px; margin-right: 15px;\">* 동 사항은 해당 카드사마다 상이할 수 있으므로 카드사의 안내에 따라 조치</p><br>\r\n\r\n[사례] 휴대품 절도<br>\r\nㅇ 란치드(사자다리), 부다왕궁, 영웅광장, 세체니 온천, 성 이쉬트반 대성당 등 관광명소에서 피해가 발생하고 있습니다.<br><br>\r\n\r\n[대책]<br>\r\nㅇ 모르는 사람이 친절하게 접근해 오면 경계심을 갖고 대응하며 특히 자신의 휴대품에 주의해야 합니다.<br>\r\nㅇ 현금은 가능한 한 의복의 내부 주머니의 넣어두고 지갑도 2곳으로 분산하여 휴대하는 것이 좋습니다.<br>\r\nㅇ 혼잡한 곳에서는 가능한 한 휴대가방을 몸의 정면에 두고 다니고, 레스토랑에서 식사하는 도중 이석할 때는 휴대품을 의자 등에 놓아두지 말고 휴대하시기 바랍니다.<br>\r\nㅇ 공항이나 호텔에서도 가방 등 휴대물품을 잠시 놓아두고 이석한 사이에 날치기 당하는 사례가 많습니다. 휴대품은 잠시라도 방치하지 마시기 바랍니다.<br><br>\r\n\r\n[사례] 노상강탈(들치기)<br>\r\nㅇ 인적이 드문 취약 지역과 기차역 주변 그리고 야간에 주의를 요합니다.<br>\r\n최근에는 대낮에 인파가 많은 곳에서도 오토바이를 탄 2인 1조가 휴대중인 가방을 들치기하는 사례가 종종 발생하고 있습니다.<br><br>\r\n\r\n[대책]<br>\r\nㅇ 도보 이동시 가방을 어깨에서 크로스로 매는 것이 좋으며, 가방끈을 짧게 조정하고 건물 쪽으로 들고 다니는 것이 안전합니다. 혼잡한 곳에서는 가능한 휴대가방을 몸의 정면에 두고 다니십시오.<br><br>\r\n\r\n[사례] 대중교통 및 열차 이용시 소지품 분실<br>\r\nㅇ 혼잡한 대중교통(버스,지하철,전차)과 열차(주로 비엔나-부다페스트, 야간) 이용시 금품, 여권 등을 도난/분실하는 사례가 발생하고 있습니다.<br><br>\r\n\r\n[대책]<br>\r\nㅇ 열차 이동시 짐은 가급적 시선이 닿는 곳에 보관합니다.(야간 기차 탑승 시 각별히 유의)<br>\r\nㅇ 가방의 지퍼를 열지 못하도록 손으로 잡고 있는 등 소매치기에 유의합니다.<br>\r\nㅇ 모르는 사람이 접근하면 경계심을 늦추지 말 것이며 음식물, 음료수를 권할 경우 절대로 입에 대지 마시기 바랍니다.<br><br>\r\n\r\n<h3 class=\"tit\">자연재해</h3>\r\nㅇ 헝가리는 태풍, 폭우, 지진 등 자연재해가 거의 발생하지 않으나, 최근 지구 온난화의 영향으로 여름철 초고온 현상, 겨울철 폭설이나 폭우 등의 이상 현상이 가끔 발생하고 있습니다.<br>\r\nㅇ 3월말과 5월말에 다뉴브(Duna)강과 티서(Tisza)강물이 범람하는 상황이 발생하기도 합니다.<br><br>\r\n\r\n<h3 class=\"tit\">유의해야할 지역</h3>\r\nㅇ 바치(Váci) 거리, 겔레르트 언덕, 부다왕궁, 오페라 등 주요 관광지, 지하철, 기차역(켈레티, 딜리, 누거티) 주변 등에서는 소매치기의 표적이 되기 쉬우므로 소지품에 주의해야 합니다.<br>\r\n<p style=\"margin-left: 15px; margin-right: 15px;\">- 특히 기차역 주변으로의 야간 출입은 삼가하시기 바랍니다.</p>\r\nㅇ 바치거리(Váci utca) 소재 주점에서 사기 피해가 종종 발생하니 주의를 요망합니다. <br>\r\n<p style=\"margin-left: 15px; margin-right: 15px;\">- 사기주점 피해 신고 전화(헝가리 경제부) : (+36 1) 483-8080 (영어 가능) </p></div>",
  "local_contact_html": "<div>\n<h3 class=\"tit\"><span style=\"color: rgb(0, 0, 0);\">대사관 연락처</span></h3>\n<p><span style=\"color: rgb(0, 0, 0);\">ㅇ 주소 : 1062 Andrassy ut. 109. Budapest, Hungary</span><br>\n<span style=\"color: rgb(0, 0, 0);\">ㅇ 대표번호(근무시간 중) : (36) 1-462-3080</span><br>\n<span style=\"color: rgb(0, 0, 0);\">ㅇ 긴급연락처(사건사고 등 긴급상황 발생 시, 24시간) : (36) 30-550-9922</span><br>\n<span style=\"color: rgb(0, 0, 0);\">ㅇ E-mail : </span><a href=\"mailto:hungary@mofa.go.kr\"><span style=\"color: rgb(0, 0, 0);\">hungary@mofa.go.kr</span></a><span style=\"color: rgb(0, 0, 0);\"> (대표이메일)</span><br>\n<a href=\"mailto:hun.consul@mofa.go.kr\"><span style=\"color: rgb(0, 0, 0);\">hun.consul@mofa.go.kr</span></a><span style=\"color: rgb(0, 0, 0);\"> (영사과 이메일)</span><br>\n<br></p>\n<h3 class=\"tit\"><span style=\"color: rgb(0, 0, 0);\">주재국 신고</span></h3>\n<p><span style=\"font-family: '맑은 고딕'; font-size: 12pt; color: rgb(0, 0, 0);\">ㅇ 경 찰 : 107</span><br>\n<span style=\"font-family: '맑은 고딕'; font-size: 12pt; color: rgb(0, 0, 0);\">ㅇ 경 찰 (외국인 여행자 사고 전담 부서(오전 8시-오후 8시)) : (+36 1)438 8080</span><br>\n<span style=\"font-family: '맑은 고딕'; font-size: 12pt; color: rgb(0, 0, 0);\">ㅇ 긴</span><span style=\"font-family: '맑은 고딕'; font-size: 12pt; color: rgb(0, 0, 0);\">급의료지원</span><br></p>\n<p style=\"margin-left: 15px; margin-right: 15px;\"><span style=\"font-family: '맑은 고딕'; font-size: 12pt; color: rgb(0, 0, 0);\">- 엠뷸런스 및 긴급의료기관 요청 : 104 </span><br>\n<span style=\"font-family: '맑은 고딕'; font-size: 12pt; color: rgb(0, 0, 0);\">- 24시간 응급치료(영어통용) : (+36 1)200 0100(페스트 지역</span><span style=\"font-family: '맑은 고딕'; font-size: 12pt; color: rgb(0, 0, 0);\">), (+36 1)212 6636(부다지역)</span></p>\n<p><span style=\"font-family: '맑은 고딕'; font-size: 12pt; color: rgb(0, 0, 0);\">ㅇ 화 재 : 105 </span><br>\n<span style=\"font-family: '맑은 고딕'; font-size: 12pt; color: rgb(0, 0, 0);\">ㅇ 자동차고장 및 견인 : 188 혹은&nbsp;</span><span style=\"font-family: '맑은 고딕'; font-size: 12pt; color: rgb(0, 0, 0);\">(+36 1)580 5134</span><br>\n<span style=\"font-family: '맑은 고딕'; font-size: 12pt; color: rgb(0, 0, 0);\">ㅇ 긴급서비스 : 112(범죄피해, 화재, 교통사고, 병원 문의 등 긴급 상황 발생 시 중앙콜센터로 영어통용)</span><br>\n<span style=\"font-family: '맑은 고딕'; font-size: 12pt; color: rgb(0, 0, 0);\">ㅇ 분실 신고 관련</span></p>\n<p><span style=\"background-color: rgb(255, 255, 255); color: rgb(0, 0, 0); font-family: '맑은 고딕'; font-size: 12pt; font-style: normal; font-variant-ligatures: normal; font-variant-caps: normal; font-weight: 400; letter-spacing: -0.39px;\">&nbsp; </span><span style=\"font-size: 12pt; font-family: '맑은 고딕'; color: rgb(0, 0, 0); letter-spacing: -0.05em;\">▶&nbsp;</span><span style=\"background-color: rgb(255, 255, 255); color: rgb(0, 0, 0); font-family: '맑은 고딕'; font-size: 12pt; font-style: normal; font-variant-ligatures: normal; font-variant-caps: normal; font-weight: 400; letter-spacing: -0.39px;\">부다페스트 공항 분실<br></span></p>\n<p style=\"font-style: normal; font-variant-ligatures: normal; font-variant-caps: normal; background-color: rgb(255, 255, 255);\"><b style=\"color: rgb(83, 83, 83); font-family: TrebuchetMS-Bold; font-size: 15px; font-weight: 400; letter-spacing: -0.39px;\"><span style=\"font-family: '맑은 고딕'; font-size: 12pt; color: rgb(0, 0, 0);\">&nbsp; &nbsp; [Celebi Gh]:</span></b><br style=\"color: rgb(83, 83, 83); font-family: Trebuchet2;\">\n <span style=\"color: rgb(0, 0, 0);\"> </span><span style=\"color: rgb(0, 0, 0); font-family: '맑은 고딕'; font-size: 12pt; font-weight: 400; letter-spacing: -0.39px;\">&nbsp; &nbsp;- T2A +36-70-332-4007, +36-1-296-5317&nbsp;</span><br style=\"color: rgb(83, 83, 83); font-family: Trebuchet2;\">\n <span style=\"color: rgb(0, 0, 0);\"> </span><span style=\"color: rgb(0, 0, 0); font-family: '맑은 고딕'; font-size: 12pt; font-weight: 400; letter-spacing: -0.39px;\">&nbsp;&nbsp; - T2B +36-70-332-4006, +36-1-296-5966&nbsp;<br></span><span style=\"color: rgb(0, 0, 0); font-family: '맑은 고딕'; font-size: 12pt; font-weight: 400; letter-spacing: -0.39px;\">&nbsp;&nbsp; - E-mail:&nbsp;</span><a href=\"mailto:LL@celebiaviation.hu\" style=\"color: rgb(205, 122, 49); font-family: Trebuchet2; font-size: 13px; font-weight: 400; letter-spacing: -0.03em; display: inline-block;\"><span style=\"font-family: '맑은 고딕'; font-size: 12pt; color: rgb(0, 0, 0);\">LL@celebiaviation.hu</span></a><br style=\"color: rgb(83, 83, 83); font-family: Trebuchet2;\">\n <span style=\"color: rgb(0, 0, 0);\"> </span><br style=\"color: rgb(83, 83, 83); font-family: Trebuchet2;\">\n <span style=\"color: rgb(0, 0, 0);\"> </span><strong style=\"color: rgb(83, 83, 83); font-family: TrebuchetMS-Bold; font-size: 15px; font-weight: 400; letter-spacing: -0.39px;\"><span style=\"font-family: '맑은 고딕'; font-size: 12pt; color: rgb(0, 0, 0);\">&nbsp;&nbsp;</span></strong><span style=\"color: rgb(0, 0, 0); font-family: '맑은 고딕'; letter-spacing: -0.8px; font-size: 12pt;\">&nbsp;[</span><strong style=\"color: rgb(83, 83, 83); font-family: TrebuchetMS-Bold; font-size: 15px; font-weight: 400; letter-spacing: -0.39px; font-style: normal; font-variant-ligatures: normal; font-variant-caps: normal;\"><span style=\"font-family: '맑은 고딕'; font-size: 12pt; color: rgb(0, 0, 0);\">AIRPORT SERVICE BUDAPEST]</span></strong></p>\n<p style=\"font-style: normal; font-variant-ligatures: normal; font-variant-caps: normal; font-weight: 400; font-size: 15px; font-family: Roboto, 'Noto Sans', 'Microsoft YaHei New', 'Microsoft Yahei', 微软雅黑, 宋体, SimSun, STXihei, 华文细黑, sans-serif; color: rgb(51, 51, 51); letter-spacing: -0.39px; background-color: rgb(255, 255, 255);\"><span style=\"font-family: '맑은 고딕'; color: rgb(0, 0, 0); font-size: 12pt;\">&nbsp; - T2A &nbsp;+36-1-296-7690</span><br style=\"color: rgb(83, 83, 83); font-family: Trebuchet2;\">\n <span style=\"color: rgb(0, 0, 0);\"> </span><span style=\"font-family: '맑은 고딕'; color: rgb(0, 0, 0); font-size: 12pt;\">&nbsp; - T2B &nbsp;+36-1-296-7473</span><br style=\"color: rgb(83, 83, 83); font-family: Trebuchet2;\">\n <span style=\"color: rgb(0, 0, 0);\"> </span><span style=\"font-family: '맑은 고딕'; color: rgb(0, 0, 0); font-size: 12pt;\">&nbsp; - Email:&nbsp;</span><a href=\"mailto:as.lostandfound@asaviaton.hu\" style=\"font-size: 13px; font-family: Trebuchet2; color: rgb(205, 122, 49); letter-spacing: -0.03em; display: inline-block;\"><span style=\"font-family: '맑은 고딕'; font-size: 12pt; color: rgb(0, 0, 0);\">as.lostandfound@asaviaton.hu</span></a><br style=\"color: rgb(83, 83, 83); font-family: Trebuchet2;\"></p>\n<p style=\"font-style: normal; font-variant-ligatures: normal; font-variant-caps: normal; font-weight: 400; font-size: 15px; font-family: Roboto, 'Noto Sans', 'Microsoft YaHei New', 'Microsoft Yahei', 微软雅黑, 宋体, SimSun, STXihei, 华文细黑, sans-serif; color: rgb(51, 51, 51); letter-spacing: -0.39px; background-color: rgb(255, 255, 255);\"><b style=\"font-family: TrebuchetMS-Bold; color: rgb(83, 83, 83);\"><span style=\"font-family: '맑은 고딕'; font-size: 12pt; color: rgb(0, 0, 0);\"><br></span></b></p>\n<p style=\"font-style: normal; font-variant-ligatures: normal; font-variant-caps: normal; font-size: 15px; font-family: Roboto, 'Noto Sans', 'Microsoft YaHei New', 'Microsoft Yahei', 微软雅黑, 宋体, SimSun, STXihei, 华文细黑, sans-serif; color: rgb(51, 51, 51); letter-spacing: -0.39px; background-color: rgb(255, 255, 255);\"><span style=\"font-family: '맑은 고딕'; color: rgb(0, 0, 0); font-size: 12pt;\">&nbsp; &nbsp;[Menzies Gh]</span><br style=\"color: rgb(83, 83, 83); font-family: Trebuchet2;\">\n <span style=\"color: rgb(0, 0, 0);\"> </span><span style=\"font-weight: 400; font-family: '맑은 고딕'; color: rgb(0, 0, 0); font-size: 12pt;\">&nbsp; - T2A: +36-1-296-8315</span><br style=\"color: rgb(83, 83, 83); font-family: Trebuchet2;\">\n <span style=\"color: rgb(0, 0, 0);\"> </span><span style=\"font-weight: 400; font-family: '맑은 고딕'; color: rgb(0, 0, 0); font-size: 12pt;\">&nbsp; - T2B: +36-1-296-8399&nbsp;</span><br style=\"color: rgb(83, 83, 83); font-family: Trebuchet2;\">\n <span style=\"color: rgb(0, 0, 0);\"> </span><span style=\"font-weight: 400; font-family: '맑은 고딕'; color: rgb(0, 0, 0); font-size: 12pt;\">&nbsp; - Email:&nbsp;</span><a href=\"mailto:bud.lostandfound@menziesaviation.com\" style=\"font-weight: 400; font-size: 13px; font-family: Trebuchet2; color: rgb(205, 122, 49); letter-spacing: -0.03em; display: inline-block;\"><span style=\"font-family: '맑은 고딕'; font-size: 12pt; color: rgb(0, 0, 0);\">bud.lostandfound@menziesaviation.com</span></a><span style=\"font-weight: 400; font-family: '맑은 고딕'; color: rgb(0, 0, 0); font-size: 12pt;\">&nbsp;</span><span style=\"font-family: '맑은 고딕'; font-size: 12pt; color: rgb(0, 0, 0);\">&nbsp;&nbsp;</span><br></p>\n<p style=\"font-style: normal; font-variant-ligatures: normal; font-variant-caps: normal; font-weight: 400; font-size: 15px; font-family: Roboto, 'Noto Sans', 'Microsoft YaHei New', 'Microsoft Yahei', 微软雅黑, 宋体, SimSun, STXihei, 华文细黑, sans-serif; color: rgb(51, 51, 51); letter-spacing: -0.39px; background-color: rgb(255, 255, 255);\"><span style=\"font-style: normal; font-variant-ligatures: normal; font-variant-caps: normal; font-weight: 400; letter-spacing: -0.39px; font-family: '맑은 고딕'; font-size: 12pt; color: rgb(0, 0, 0);\">&nbsp;※ 항공사별 분실물센터 확인 :&nbsp;&nbsp;</span><a href=\"https://www.bud.hu/en/passengers/flight_and_travel_information/travel_information/lost_baggage\" style=\"font-family: Roboto, 'Noto Sans', 'Microsoft YaHei New', 'Microsoft Yahei', 微软雅黑, 宋体, SimSun, STXihei, 华文细黑, sans-serif; font-size: 15px; font-style: normal; font-variant-ligatures: normal; font-variant-caps: normal; font-weight: 400; color: rgb(51, 51, 51); letter-spacing: -0.03em;\"><span style=\"font-family: '맑은 고딕'; font-size: 12pt; color: rgb(0, 0, 0);\">https://www.bud.hu/en/passengers/flight_and_travel_information/travel_information/lost_baggage</span></a></p>\n<p style=\"font-style: normal; font-variant-ligatures: normal; font-variant-caps: normal; font-weight: 400; font-size: 15px; font-family: Roboto, 'Noto Sans', 'Microsoft YaHei New', 'Microsoft Yahei', 微软雅黑, 宋体, SimSun, STXihei, 华文细黑, sans-serif; color: rgb(51, 51, 51); letter-spacing: -0.39px; background-color: rgb(255, 255, 255);\"><span style=\"font-family: '맑은 고딕'; font-size: 12pt; color: rgb(0, 0, 0);\">&nbsp;</span></p>\n<p style=\"font-style: normal; font-variant-ligatures: normal; font-variant-caps: normal; font-weight: 400; font-size: 15px; font-family: Roboto, 'Noto Sans', 'Microsoft YaHei New', 'Microsoft Yahei', 微软雅黑, 宋体, SimSun, STXihei, 华文细黑, sans-serif; color: rgb(51, 51, 51); letter-spacing: -0.39px; background-color: rgb(255, 255, 255);\"><span style=\"background-color: rgb(255, 255, 255); font-style: normal; font-variant-ligatures: normal; font-variant-caps: normal; font-weight: 400; letter-spacing: -0.39px; font-size: 12pt; font-family: '맑은 고딕'; color: rgb(0, 0, 0);\">&nbsp;</span><span style=\"font-style: normal; font-variant-ligatures: normal; font-variant-caps: normal; font-weight: 400; font-size: 12pt; font-family: '맑은 고딕'; color: rgb(0, 0, 0); letter-spacing: -0.05em;\">▶&nbsp;</span><span style=\"font-style: normal; font-variant-ligatures: normal; font-variant-caps: normal; font-weight: 400; letter-spacing: -0.39px; font-family: '맑은 고딕'; font-size: 12pt; color: rgb(0, 0, 0);\">부다페스트 기차 및 기차역 분실</span></p>\n<p style=\"font-style: normal; font-variant-ligatures: normal; font-variant-caps: normal; font-weight: 400; font-size: 15px; font-family: Roboto, 'Noto Sans', 'Microsoft YaHei New', 'Microsoft Yahei', 微软雅黑, 宋体, SimSun, STXihei, 华文细黑, sans-serif; color: rgb(51, 51, 51); letter-spacing: -0.39px; background-color: rgb(255, 255, 255);\"><span style=\"font-family: '맑은 고딕'; font-size: 12pt; color: rgb(0, 0, 0);\">&nbsp; &nbsp;-&nbsp;연락처 : +36 (1) 349 4949 전화 건 후 6번 메뉴 선택</span><br>\n<span style=\"font-family: '맑은 고딕'; font-size: 12pt; color: rgb(0, 0, 0);\">&nbsp; &nbsp;-&nbsp;이메일 :&nbsp;</span><a href=\"mailto:informacio@mav-start.hu\" style=\"color: rgb(51, 51, 51); letter-spacing: -0.03em;\"><span style=\"font-family: '맑은 고딕'; font-size: 12pt; color: rgb(0, 0, 0);\">informacio@mav-start.hu</span></a></p>\n<p style=\"font-style: normal; font-variant-ligatures: normal; font-variant-caps: normal; font-weight: 400; font-size: 15px; font-family: Roboto, 'Noto Sans', 'Microsoft YaHei New', 'Microsoft Yahei', 微软雅黑, 宋体, SimSun, STXihei, 华文细黑, sans-serif; color: rgb(51, 51, 51); letter-spacing: -0.39px; background-color: rgb(255, 255, 255);\"><span style=\"font-family: '맑은 고딕'; font-size: 12pt; color: rgb(0, 0, 0);\">&nbsp; * 분실 습득물은 최대 3개월 보관</span></p>\n<p style=\"font-style: normal; font-variant-ligatures: normal; font-variant-caps: normal; font-weight: 400; font-size: 15px; font-family: Roboto, 'Noto Sans', 'Microsoft YaHei New', 'Microsoft Yahei', 微软雅黑, 宋体, SimSun, STXihei, 华文细黑, sans-serif; color: rgb(51, 51, 51); letter-spacing: -0.39px; background-color: rgb(255, 255, 255);\"><span style=\"font-family: '맑은 고딕'; font-size: 12pt; color: rgb(0, 0, 0);\"><br></span></p>\n<p style=\"font-style: normal; font-variant-ligatures: normal; font-variant-caps: normal; font-weight: 400; font-size: 15px; font-family: Roboto, 'Noto Sans', 'Microsoft YaHei New', 'Microsoft Yahei', 微软雅黑, 宋体, SimSun, STXihei, 华文细黑, sans-serif; color: rgb(51, 51, 51); letter-spacing: -0.39px; background-color: rgb(255, 255, 255);\"><span style=\"font-family: '맑은 고딕'; font-size: 12pt; color: rgb(0, 0, 0);\">&nbsp;</span><span style=\"font-size: 12pt; font-style: normal; font-variant-ligatures: normal; font-variant-caps: normal; font-weight: 400; font-family: '맑은 고딕'; color: rgb(0, 0, 0); letter-spacing: -0.05em;\">▶&nbsp;</span><span style=\"background-color: rgb(255, 255, 255); font-family: '맑은 고딕'; font-size: 12pt; font-style: normal; font-variant-ligatures: normal; font-variant-caps: normal; font-weight: 400; letter-spacing: -0.39px; color: rgb(0, 0, 0);\">대중교통(BKK) 이용시 분실</span></p>\n<p style=\"font-style: normal; font-variant-ligatures: normal; font-variant-caps: normal; font-size: 15px; font-family: Roboto, 'Noto Sans', 'Microsoft YaHei New', 'Microsoft Yahei', 微软雅黑, 宋体, SimSun, STXihei, 华文细黑, sans-serif; color: rgb(51, 51, 51); letter-spacing: -0.39px; background-color: rgb(255, 255, 255);\"><span style=\"font-weight: 400; font-family: '맑은 고딕'; font-size: 12pt; color: rgb(0, 0, 0);\">&nbsp; &nbsp;-&nbsp;연락처 : +36 (1) 3 255 255 전화 건 후 1.6번 메뉴 선택 - (화/목) 10:00~14:00 에만 통화가능<br>&nbsp; &nbsp;-&nbsp;주소 : 107</span><span style=\"font-family: '맑은 고딕'; font-size: 12pt; color: rgb(0, 0, 0);\">2 Budapest, Ak&aacute;cfa u. 18.</span><br>\n<span style=\"font-family: '맑은 고딕'; font-size: 12pt; color: rgb(0, 0, 0);\">&nbsp; &nbsp;-&nbsp;이메일 :&nbsp;</span><a data-user=\"talalttargy\" data-host=\"bkv.hu\" style=\"font-size: 16px; font-family: 'Open Sans', sans-serif; color: rgb(51, 51, 51); letter-spacing: -0.03em;\"><span style=\"font-family: '맑은 고딕'; font-size: 12pt; color: rgb(0, 0, 0);\">talalttargy@bkv.hu</span></a></p>\n<p style=\"font-style: normal; font-variant-ligatures: normal; font-variant-caps: normal; font-weight: 400; font-size: 13px; font-family: 'Malgun Gothic', Dotum, Gulim, Arial, Verdana, Tahoma; color: rgb(51, 51, 51); letter-spacing: -0.39px; background-color: rgb(255, 255, 255);\"><span style=\"font-family: Roboto, 'Noto Sans', 'Microsoft YaHei New', 'Microsoft Yahei', 微软雅黑, 宋体, SimSun, STXihei, 华文细黑, sans-serif;\"><span style=\"font-size: 12pt; font-family: '맑은 고딕'; color: rgb(0, 0, 0);\">&nbsp; &nbsp;-&nbsp;근무시간 : (화~목) 10:00~16:00</span></span><br>\n<span style=\"font-family: Roboto, 'Noto Sans', 'Microsoft YaHei New', 'Microsoft Yahei', 微软雅黑, 宋体, SimSun, STXihei, 华文细黑, sans-serif;\"><span style=\"font-size: 12pt; font-family: '맑은 고딕'; color: rgb(0, 0, 0);\">&nbsp;&nbsp;&nbsp; ※ 분실자가 제공하는 분실일자, 시간, 장소 및 분실물 정보(색, 크기, 브랜드 등)와 분실물이 일치하면, 신분증 제출 및 행정수수료 납부 후 위 주소지에서 수령 가능(당사자 직접 방문)</span></span></p>\n<p style=\"font-style: normal; font-variant-ligatures: normal; font-variant-caps: normal; font-weight: 400; font-size: 13px; font-family: 'Malgun Gothic', Dotum, Gulim, Arial, Verdana, Tahoma; color: rgb(51, 51, 51); letter-spacing: -0.39px; background-color: rgb(255, 255, 255);\"><span style=\"font-family: '맑은 고딕'; font-size: 12pt; color: rgb(0, 0, 0);\">&nbsp; &nbsp;-&nbsp;관련 안내 홈페이지 : </span><a href=\"https://bkk.hu/en/about-bkk/contacts/other-issues/\" target=\"_blank\"><span style=\"font-family: '맑은 고딕'; font-size: 12pt; color: rgb(0, 0, 0);\">https://bkk.hu/en/about-bkk/contacts/other-issues/</span></a></p>\n<h3 class=\"tit\"><span style=\"font-family: '맑은 고딕'; color: rgb(0, 0, 0);\">의료기관 연락처</span></h3>\n<p><span style=\"font-family: 'Malgun Gothic'; font-size: 16px; font-style: normal; font-variant-ligatures: normal; font-variant-caps: normal; font-weight: 400; letter-spacing: -0.4px; color: rgb(0, 0, 0);\">ㅇ&nbsp;</span><span style=\"font-family: '맑은 고딕'; color: rgb(0, 0, 0);\">부다페스트 내 종합병원</span></p>\n<p><span style=\"color: rgb(0, 0, 0); font-family: NBG, Arial, sans-serif; font-size: 14px; font-style: normal; font-variant-ligatures: normal; font-variant-caps: normal; font-weight: 400; letter-spacing: 0.112px; word-spacing: -0.35px; background-color: rgb(255, 254, 250);\">&nbsp;1) Szent J&aacute;nos K&oacute;rh&aacute;z - 응급 / 종합</span><br style=\"letter-spacing: -0.025em; word-spacing: -0.35px; color: rgb(51, 51, 51); font-family: NBG, Arial, sans-serif; font-size: 14px; background-color: rgb(255, 254, 250);\">\n <span style=\"color: rgb(0, 0, 0); font-family: NBG, Arial, sans-serif; font-size: 14px; font-style: normal; font-variant-ligatures: normal; font-variant-caps: normal; font-weight: 400; letter-spacing: 0.112px; word-spacing: -0.35px; background-color: rgb(255, 254, 250);\">&nbsp; -&nbsp;주소 : 1125 Budapest, Di&oacute;s &aacute;rok 1-3.</span><br style=\"letter-spacing: -0.025em; word-spacing: -0.35px; color: rgb(51, 51, 51); font-family: NBG, Arial, sans-serif; font-size: 14px; background-color: rgb(255, 254, 250);\">\n <span style=\"color: rgb(0, 0, 0); font-family: NBG, Arial, sans-serif; font-size: 14px; font-style: normal; font-variant-ligatures: normal; font-variant-caps: normal; font-weight: 400; letter-spacing: 0.112px; word-spacing: -0.35px; background-color: rgb(255, 254, 250);\">&nbsp; -&nbsp;전화 : (+36 1) 458 4500</span><br style=\"letter-spacing: -0.025em; word-spacing: -0.35px; color: rgb(51, 51, 51); font-family: NBG, Arial, sans-serif; font-size: 14px; background-color: rgb(255, 254, 250);\">\n <span style=\"color: rgb(0, 0, 0); font-family: NBG, Arial, sans-serif; font-size: 14px; font-style: normal; font-variant-ligatures: normal; font-variant-caps: normal; font-weight: 400; letter-spacing: 0.112px; word-spacing: -0.35px; background-color: rgb(255, 254, 250);\">&nbsp; -&nbsp;근무시간 : 24시간</span><br style=\"letter-spacing: -0.025em; word-spacing: -0.35px; color: rgb(51, 51, 51); font-family: NBG, Arial, sans-serif; font-size: 14px; background-color: rgb(255, 254, 250);\">\n <br style=\"letter-spacing: -0.025em; word-spacing: -0.35px; color: rgb(51, 51, 51); font-family: NBG, Arial, sans-serif; font-size: 14px; background-color: rgb(255, 254, 250);\">\n <span style=\"color: rgb(0, 0, 0); font-family: NBG, Arial, sans-serif; font-size: 14px; font-style: normal; font-variant-ligatures: normal; font-variant-caps: normal; font-weight: 400; letter-spacing: 0.112px; word-spacing: -0.35px; background-color: rgb(255, 254, 250);\">&nbsp;2) Uzsoki Utcai Korh&aacute;z(응급실)</span><br style=\"letter-spacing: -0.025em; word-spacing: -0.35px; color: rgb(51, 51, 51); font-family: NBG, Arial, sans-serif; font-size: 14px; background-color: rgb(255, 254, 250);\">\n <span style=\"color: rgb(0, 0, 0); font-family: NBG, Arial, sans-serif; font-size: 14px; font-style: normal; font-variant-ligatures: normal; font-variant-caps: normal; font-weight: 400; letter-spacing: 0.112px; word-spacing: -0.35px; background-color: rgb(255, 254, 250);\">&nbsp; -&nbsp;주소: 1145 Budapest, Uzsoki u.29-41</span><br style=\"letter-spacing: -0.025em; word-spacing: -0.35px; color: rgb(51, 51, 51); font-family: NBG, Arial, sans-serif; font-size: 14px; background-color: rgb(255, 254, 250);\">\n <span style=\"color: rgb(0, 0, 0); font-family: NBG, Arial, sans-serif; font-size: 14px; font-style: normal; font-variant-ligatures: normal; font-variant-caps: normal; font-weight: 400; letter-spacing: 0.112px; word-spacing: -0.35px; background-color: rgb(255, 254, 250);\">&nbsp; -&nbsp;연락처: (+36&nbsp;1)&nbsp;467&nbsp;3700</span><br style=\"letter-spacing: -0.025em; word-spacing: -0.35px; color: rgb(51, 51, 51); font-family: NBG, Arial, sans-serif; font-size: 14px; background-color: rgb(255, 254, 250);\">\n <br style=\"letter-spacing: -0.025em; word-spacing: -0.35px; color: rgb(51, 51, 51); font-family: NBG, Arial, sans-serif; font-size: 14px; background-color: rgb(255, 254, 250);\">\n <span style=\"color: rgb(0, 0, 0); font-family: NBG, Arial, sans-serif; font-size: 14px; font-style: normal; font-variant-ligatures: normal; font-variant-caps: normal; font-weight: 400; letter-spacing: 0.112px; word-spacing: -0.35px; background-color: rgb(255, 254, 250);\">&nbsp;3) P&eacute;terfy K&oacute;rh&aacute;z - 외상센터 / 응급 / 교통사고 전문</span><br style=\"letter-spacing: -0.025em; word-spacing: -0.35px; color: rgb(51, 51, 51); font-family: NBG, Arial, sans-serif; font-size: 14px; background-color: rgb(255, 254, 250);\">\n <span style=\"color: rgb(0, 0, 0); font-family: NBG, Arial, sans-serif; font-size: 14px; font-style: normal; font-variant-ligatures: normal; font-variant-caps: normal; font-weight: 400; letter-spacing: 0.112px; word-spacing: -0.35px; background-color: rgb(255, 254, 250);\">&nbsp; -&nbsp;주소 : 1081 Budapest, Fiumei &uacute;t 17</span><br style=\"letter-spacing: -0.025em; word-spacing: -0.35px; color: rgb(51, 51, 51); font-family: NBG, Arial, sans-serif; font-size: 14px; background-color: rgb(255, 254, 250);\">\n <span style=\"color: rgb(0, 0, 0); font-family: NBG, Arial, sans-serif; font-size: 14px; font-style: normal; font-variant-ligatures: normal; font-variant-caps: normal; font-weight: 400; letter-spacing: 0.112px; word-spacing: -0.35px; background-color: rgb(255, 254, 250);\">&nbsp; -&nbsp;연락처 : (+36 1) 299 7700</span><br style=\"letter-spacing: -0.025em; word-spacing: -0.35px; color: rgb(51, 51, 51); font-family: NBG, Arial, sans-serif; font-size: 14px; background-color: rgb(255, 254, 250);\">\n <span style=\"color: rgb(0, 0, 0); font-family: NBG, Arial, sans-serif; font-size: 14px; font-style: normal; font-variant-ligatures: normal; font-variant-caps: normal; font-weight: 400; letter-spacing: 0.112px; word-spacing: -0.35px; background-color: rgb(255, 254, 250);\">&nbsp; -&nbsp;근무시간 : 24시간</span><br style=\"letter-spacing: -0.025em; word-spacing: -0.35px; color: rgb(51, 51, 51); font-family: NBG, Arial, sans-serif; font-size: 14px; background-color: rgb(255, 254, 250);\">\n <br style=\"letter-spacing: -0.025em; word-spacing: -0.35px; color: rgb(51, 51, 51); font-family: NBG, Arial, sans-serif; font-size: 14px; background-color: rgb(255, 254, 250);\">\n <span style=\"color: rgb(0, 0, 0); font-family: NBG, Arial, sans-serif; font-size: 14px; font-style: normal; font-variant-ligatures: normal; font-variant-caps: normal; font-weight: 400; letter-spacing: 0.112px; word-spacing: -0.35px; background-color: rgb(255, 254, 250);\">&nbsp;4) MK Honv&eacute;dk&oacute;rh&aacute;z - 응급 / 종합</span><br style=\"letter-spacing: -0.025em; word-spacing: -0.35px; color: rgb(51, 51, 51); font-family: NBG, Arial, sans-serif; font-size: 14px; background-color: rgb(255, 254, 250);\">\n <span style=\"color: rgb(0, 0, 0); font-family: NBG, Arial, sans-serif; font-size: 14px; font-style: normal; font-variant-ligatures: normal; font-variant-caps: normal; font-weight: 400; letter-spacing: 0.112px; word-spacing: -0.35px; background-color: rgb(255, 254, 250);\">&nbsp; -&nbsp;주소 : 1134 Budapest, R&oacute;bert K&aacute;roly k&ouml;r&uacute;t 44</span><br style=\"letter-spacing: -0.025em; word-spacing: -0.35px; color: rgb(51, 51, 51); font-family: NBG, Arial, sans-serif; font-size: 14px; background-color: rgb(255, 254, 250);\">\n <span style=\"color: rgb(0, 0, 0); font-family: NBG, Arial, sans-serif; font-size: 14px; font-style: normal; font-variant-ligatures: normal; font-variant-caps: normal; font-weight: 400; letter-spacing: 0.112px; word-spacing: -0.35px; background-color: rgb(255, 254, 250);\">&nbsp; -&nbsp;연락처: (+36 1) 465 1800</span><br style=\"letter-spacing: -0.025em; word-spacing: -0.35px; color: rgb(51, 51, 51); font-family: NBG, Arial, sans-serif; font-size: 14px; background-color: rgb(255, 254, 250);\">\n <span style=\"color: rgb(0, 0, 0); font-family: NBG, Arial, sans-serif; font-size: 14px; font-style: normal; font-variant-ligatures: normal; font-variant-caps: normal; font-weight: 400; letter-spacing: 0.112px; word-spacing: -0.35px; background-color: rgb(255, 254, 250);\">&nbsp; -&nbsp;근무시간 : 24시간</span><br style=\"letter-spacing: -0.025em; word-spacing: -0.35px; color: rgb(51, 51, 51); font-family: NBG, Arial, sans-serif; font-size: 14px; background-color: rgb(255, 254, 250);\">\n <br style=\"letter-spacing: -0.025em; word-spacing: -0.35px; color: rgb(51, 51, 51); font-family: NBG, Arial, sans-serif; font-size: 14px; background-color: rgb(255, 254, 250);\">\n <span style=\"color: rgb(0, 0, 0); font-family: NBG, Arial, sans-serif; font-size: 14px; font-style: normal; font-variant-ligatures: normal; font-variant-caps: normal; font-weight: 400; letter-spacing: 0.112px; word-spacing: -0.35px; background-color: rgb(255, 254, 250);\">&nbsp;5) Heim P&aacute;l k&oacute;rh&aacute;z - 응급(아동)</span><br style=\"letter-spacing: -0.025em; word-spacing: -0.35px; color: rgb(51, 51, 51); font-family: NBG, Arial, sans-serif; font-size: 14px; background-color: rgb(255, 254, 250);\">\n <span style=\"color: rgb(0, 0, 0); font-family: NBG, Arial, sans-serif; font-size: 14px; font-style: normal; font-variant-ligatures: normal; font-variant-caps: normal; font-weight: 400; letter-spacing: 0.112px; word-spacing: -0.35px; background-color: rgb(255, 254, 250);\">&nbsp; -&nbsp;주소 : 1089 Budapest, &Uuml;llői &uacute;t. 86</span><br style=\"letter-spacing: -0.025em; word-spacing: -0.35px; color: rgb(51, 51, 51); font-family: NBG, Arial, sans-serif; font-size: 14px; background-color: rgb(255, 254, 250);\">\n <span style=\"color: rgb(0, 0, 0); font-family: NBG, Arial, sans-serif; font-size: 14px; font-style: normal; font-variant-ligatures: normal; font-variant-caps: normal; font-weight: 400; letter-spacing: 0.112px; word-spacing: -0.35px; background-color: rgb(255, 254, 250);\">&nbsp; -&nbsp;연락처: (+36 1) 459 9100</span><br style=\"letter-spacing: -0.025em; word-spacing: -0.35px; color: rgb(51, 51, 51); font-family: NBG, Arial, sans-serif; font-size: 14px; background-color: rgb(255, 254, 250);\">\n <span style=\"color: rgb(0, 0, 0); font-family: NBG, Arial, sans-serif; font-size: 14px; font-style: normal; font-variant-ligatures: normal; font-variant-caps: normal; font-weight: 400; letter-spacing: 0.112px; word-spacing: -0.35px; background-color: rgb(255, 254, 250);\">&nbsp; -&nbsp;근무시간 : 24시간</span><br style=\"letter-spacing: -0.025em; word-spacing: -0.35px; color: rgb(51, 51, 51); font-family: NBG, Arial, sans-serif; font-size: 14px; background-color: rgb(255, 254, 250);\">\n <br style=\"letter-spacing: -0.025em; word-spacing: -0.35px; color: rgb(51, 51, 51); font-family: NBG, Arial, sans-serif; font-size: 14px; background-color: rgb(255, 254, 250);\">\n <span style=\"color: rgb(0, 0, 0); font-family: NBG, Arial, sans-serif; font-size: 14px; font-style: normal; font-variant-ligatures: normal; font-variant-caps: normal; font-weight: 400; letter-spacing: 0.112px; word-spacing: -0.35px; background-color: rgb(255, 254, 250);\">&nbsp;6) Szent Imre K&oacute;rh&aacute;z</span><br style=\"letter-spacing: -0.025em; word-spacing: -0.35px; color: rgb(51, 51, 51); font-family: NBG, Arial, sans-serif; font-size: 14px; background-color: rgb(255, 254, 250);\">\n <span style=\"color: rgb(0, 0, 0); font-family: NBG, Arial, sans-serif; font-size: 14px; font-style: normal; font-variant-ligatures: normal; font-variant-caps: normal; font-weight: 400; letter-spacing: 0.112px; word-spacing: -0.35px; background-color: rgb(255, 254, 250);\">&nbsp; -&nbsp;주소 : 1115 Budapest, T&eacute;t&eacute;nyi &uacute;t 12-16.</span><br style=\"letter-spacing: -0.025em; word-spacing: -0.35px; color: rgb(51, 51, 51); font-family: NBG, Arial, sans-serif; font-size: 14px; background-color: rgb(255, 254, 250);\">\n <span style=\"color: rgb(0, 0, 0); font-family: NBG, Arial, sans-serif; font-size: 14px; font-style: normal; font-variant-ligatures: normal; font-variant-caps: normal; font-weight: 400; letter-spacing: 0.112px; word-spacing: -0.35px; background-color: rgb(255, 254, 250);\">&nbsp; -&nbsp;전화 : (+36 1)464 8600</span><br style=\"letter-spacing: -0.025em; word-spacing: -0.35px; color: rgb(51, 51, 51); font-family: NBG, Arial, sans-serif; font-size: 14px; background-color: rgb(255, 254, 250);\">\n <br style=\"letter-spacing: -0.025em; word-spacing: -0.35px; color: rgb(51, 51, 51); font-family: NBG, Arial, sans-serif; font-size: 14px; background-color: rgb(255, 254, 250);\">\n <span style=\"color: rgb(0, 0, 0); font-family: NBG, Arial, sans-serif; font-size: 14px; font-style: normal; font-variant-ligatures: normal; font-variant-caps: normal; font-weight: 400; letter-spacing: 0.112px; word-spacing: -0.35px; background-color: rgb(255, 254, 250);\">&nbsp; 7) FirstMed (예약필수)</span><br style=\"letter-spacing: -0.025em; word-spacing: -0.35px; color: rgb(51, 51, 51); font-family: NBG, Arial, sans-serif; font-size: 14px; background-color: rgb(255, 254, 250);\">\n <span style=\"color: rgb(0, 0, 0); font-family: NBG, Arial, sans-serif; font-size: 14px; font-style: normal; font-variant-ligatures: normal; font-variant-caps: normal; font-weight: 400; letter-spacing: 0.112px; word-spacing: -0.35px; background-color: rgb(255, 254, 250);\">&nbsp; -&nbsp;주소 : 1015 Budapest, Hatty&uacute; u. 14</span><br style=\"letter-spacing: -0.025em; word-spacing: -0.35px; color: rgb(51, 51, 51); font-family: NBG, Arial, sans-serif; font-size: 14px; background-color: rgb(255, 254, 250);\">\n <span style=\"color: rgb(0, 0, 0); font-family: NBG, Arial, sans-serif; font-size: 14px; font-style: normal; font-variant-ligatures: normal; font-variant-caps: normal; font-weight: 400; letter-spacing: 0.112px; word-spacing: -0.35px; background-color: rgb(255, 254, 250);\">&nbsp; -&nbsp;연락처 : (+36 1) 224 9090 &lt;24시간&gt;</span><br style=\"letter-spacing: -0.025em; word-spacing: -0.35px; color: rgb(51, 51, 51); font-family: NBG, Arial, sans-serif; font-size: 14px; background-color: rgb(255, 254, 250);\">\n <span style=\"color: rgb(0, 0, 0); font-family: NBG, Arial, sans-serif; font-size: 14px; font-style: normal; font-variant-ligatures: normal; font-variant-caps: normal; font-weight: 400; letter-spacing: 0.112px; word-spacing: -0.35px; background-color: rgb(255, 254, 250);\">&nbsp; -&nbsp;근무시간 : (월-금) 08.00-20.00 / (토) 09.00-15.00</span><br style=\"letter-spacing: -0.025em; word-spacing: -0.35px; color: rgb(51, 51, 51); font-family: NBG, Arial, sans-serif; font-size: 14px; background-color: rgb(255, 254, 250);\">\n <br style=\"letter-spacing: -0.025em; word-spacing: -0.35px; color: rgb(51, 51, 51); font-family: NBG, Arial, sans-serif; font-size: 14px; background-color: rgb(255, 254, 250);\">\n <span style=\"color: rgb(0, 0, 0); font-family: NBG, Arial, sans-serif; font-size: 14px; font-style: normal; font-variant-ligatures: normal; font-variant-caps: normal; font-weight: 400; letter-spacing: 0.112px; word-spacing: -0.35px; background-color: rgb(255, 254, 250);\">&nbsp;&nbsp;8) Medicover (예약필수)</span><br style=\"letter-spacing: -0.025em; word-spacing: -0.35px; color: rgb(51, 51, 51); font-family: NBG, Arial, sans-serif; font-size: 14px; background-color: rgb(255, 254, 250);\">\n <span style=\"color: rgb(0, 0, 0); font-family: NBG, Arial, sans-serif; font-size: 14px; font-style: normal; font-variant-ligatures: normal; font-variant-caps: normal; font-weight: 400; letter-spacing: 0.112px; word-spacing: -0.35px; background-color: rgb(255, 254, 250);\">&nbsp; &nbsp;-&nbsp;가까운 병원찾기 :&nbsp;</span><a href=\"https://medicover.hu/klinikaink\" style=\"letter-spacing: -0.025em; word-spacing: -0.35px; vertical-align: middle; font-family: NBG, Arial, sans-serif; color: blue; font-size: 14px; font-style: normal; font-variant-ligatures: normal; font-variant-caps: normal; font-weight: 400; background-color: rgb(255, 254, 250);\"><span style=\"color: rgb(0, 0, 0);\">medicover.hu/klinikaink</span></a><br style=\"letter-spacing: -0.025em; word-spacing: -0.35px; color: rgb(51, 51, 51); font-family: NBG, Arial, sans-serif; font-size: 14px; background-color: rgb(255, 254, 250);\">\n <span style=\"color: rgb(0, 0, 0); font-family: NBG, Arial, sans-serif; font-size: 14px; font-style: normal; font-variant-ligatures: normal; font-variant-caps: normal; font-weight: 400; letter-spacing: 0.112px; word-spacing: -0.35px; background-color: rgb(255, 254, 250);\">&nbsp; &nbsp;-&nbsp;연락처 : (+36 1) 465 3100 / (+36 1) 465 3101 &lt;24시간 상담&gt;</span><br style=\"letter-spacing: -0.025em; word-spacing: -0.35px; color: rgb(51, 51, 51); font-family: NBG, Arial, sans-serif; font-size: 14px; background-color: rgb(255, 254, 250);\">\n <span style=\"color: rgb(0, 0, 0); font-family: NBG, Arial, sans-serif; font-size: 14px; font-style: normal; font-variant-ligatures: normal; font-variant-caps: normal; font-weight: 400; letter-spacing: 0.112px; word-spacing: -0.35px; background-color: rgb(255, 254, 250);\">&nbsp; &nbsp;-&nbsp;근무시간 : (월-금) 07.00-20.00</span><br style=\"letter-spacing: -0.025em; word-spacing: -0.35px; color: rgb(51, 51, 51); font-family: NBG, Arial, sans-serif; font-size: 14px; background-color: rgb(255, 254, 250);\">\n <br style=\"letter-spacing: -0.025em; word-spacing: -0.35px; color: rgb(51, 51, 51); font-family: NBG, Arial, sans-serif; font-size: 14px; background-color: rgb(255, 254, 250);\">\n <span style=\"color: rgb(0, 0, 0); font-family: NBG, Arial, sans-serif; font-size: 14px; font-style: normal; font-variant-ligatures: normal; font-variant-caps: normal; font-weight: 400; letter-spacing: 0.112px; word-spacing: -0.35px; background-color: rgb(255, 254, 250);\">&nbsp; 9) Emineo Mag&aacute;nk&oacute;rh&aacute;z (예약필수)</span><br style=\"letter-spacing: -0.025em; word-spacing: -0.35px; color: rgb(51, 51, 51); font-family: NBG, Arial, sans-serif; font-size: 14px; background-color: rgb(255, 254, 250);\">\n <span style=\"color: rgb(0, 0, 0); font-family: NBG, Arial, sans-serif; font-size: 14px; font-style: normal; font-variant-ligatures: normal; font-variant-caps: normal; font-weight: 400; letter-spacing: 0.112px; word-spacing: -0.35px; background-color: rgb(255, 254, 250);\">&nbsp; -&nbsp;주소 : 1016 Budapest, Hegyalja &uacute;t 7-13</span><br style=\"letter-spacing: -0.025em; word-spacing: -0.35px; color: rgb(51, 51, 51); font-family: NBG, Arial, sans-serif; font-size: 14px; background-color: rgb(255, 254, 250);\">\n <span style=\"color: rgb(0, 0, 0); font-family: NBG, Arial, sans-serif; font-size: 14px; font-style: normal; font-variant-ligatures: normal; font-variant-caps: normal; font-weight: 400; letter-spacing: 0.112px; word-spacing: -0.35px; background-color: rgb(255, 254, 250);\">&nbsp; -&nbsp;연락처 : (+36 1) 203 1288</span><br style=\"letter-spacing: -0.025em; word-spacing: -0.35px; color: rgb(51, 51, 51); font-family: NBG, Arial, sans-serif; font-size: 14px; background-color: rgb(255, 254, 250);\">\n <span style=\"color: rgb(0, 0, 0); font-family: NBG, Arial, sans-serif; font-size: 14px; font-style: normal; font-variant-ligatures: normal; font-variant-caps: normal; font-weight: 400; letter-spacing: 0.112px; word-spacing: -0.35px; background-color: rgb(255, 254, 250);\">&nbsp; &nbsp;-&nbsp;근무시간 : (월-일) 08.00-20.00</span><br style=\"letter-spacing: -0.025em; word-spacing: -0.35px; color: rgb(51, 51, 51); font-family: NBG, Arial, sans-serif; font-size: 14px; background-color: rgb(255, 254, 250);\">\n <br style=\"letter-spacing: -0.025em; word-spacing: -0.35px; color: rgb(51, 51, 51); font-family: NBG, Arial, sans-serif; font-size: 14px; background-color: rgb(255, 254, 250);\">\n <span style=\"color: rgb(0, 0, 0); font-family: NBG, Arial, sans-serif; font-size: 14px; font-style: normal; font-variant-ligatures: normal; font-variant-caps: normal; font-weight: 400; letter-spacing: 0.112px; word-spacing: -0.35px; background-color: rgb(255, 254, 250);\">&nbsp;10) Waberer Medical Center(예약필수)</span><br style=\"letter-spacing: -0.025em; word-spacing: -0.35px; color: rgb(51, 51, 51); font-family: NBG, Arial, sans-serif; font-size: 14px; background-color: rgb(255, 254, 250);\">\n <span style=\"color: rgb(0, 0, 0); font-family: NBG, Arial, sans-serif; font-size: 14px; font-style: normal; font-variant-ligatures: normal; font-variant-caps: normal; font-weight: 400; letter-spacing: 0.112px; word-spacing: -0.35px; background-color: rgb(255, 254, 250);\">&nbsp; -&nbsp;주소: 1123 Budapest, Alkot&aacute;s u.55-61</span><br style=\"letter-spacing: -0.025em; word-spacing: -0.35px; color: rgb(51, 51, 51); font-family: NBG, Arial, sans-serif; font-size: 14px; background-color: rgb(255, 254, 250);\">\n <span style=\"color: rgb(0, 0, 0); font-family: NBG, Arial, sans-serif; font-size: 14px; font-style: normal; font-variant-ligatures: normal; font-variant-caps: normal; font-weight: 400; letter-spacing: 0.112px; word-spacing: -0.35px; background-color: rgb(255, 254, 250);\">&nbsp; -&nbsp;연락처: (+36&nbsp;1)&nbsp;323&nbsp;7000</span><br style=\"letter-spacing: -0.025em; word-spacing: -0.35px; color: rgb(51, 51, 51); font-family: NBG, Arial, sans-serif; font-size: 14px; background-color: rgb(255, 254, 250);\">\n <span style=\"color: rgb(0, 0, 0); font-family: NBG, Arial, sans-serif; font-size: 14px; font-style: normal; font-variant-ligatures: normal; font-variant-caps: normal; font-weight: 400; letter-spacing: 0.112px; word-spacing: -0.35px; background-color: rgb(255, 254, 250);\">&nbsp; -&nbsp;근무시간: (월-금) 07.00-20.00</span><br style=\"letter-spacing: -0.025em; word-spacing: -0.35px; color: rgb(51, 51, 51); font-family: NBG, Arial, sans-serif; font-size: 14px; background-color: rgb(255, 254, 250);\">\n <br style=\"letter-spacing: -0.025em; word-spacing: -0.35px; color: rgb(51, 51, 51); font-family: NBG, Arial, sans-serif; font-size: 14px; background-color: rgb(255, 254, 250);\">\n <span style=\"color: rgb(0, 0, 0); font-family: NBG, Arial, sans-serif; font-size: 14px; font-style: normal; font-variant-ligatures: normal; font-variant-caps: normal; font-weight: 400; letter-spacing: 0.112px; word-spacing: -0.35px; background-color: rgb(255, 254, 250);\">&nbsp;11) R&oacute;zsakert Medical Center (예약필수)</span><br style=\"letter-spacing: -0.025em; word-spacing: -0.35px; color: rgb(51, 51, 51); font-family: NBG, Arial, sans-serif; font-size: 14px; background-color: rgb(255, 254, 250);\">\n <span style=\"color: rgb(0, 0, 0); font-family: NBG, Arial, sans-serif; font-size: 14px; font-style: normal; font-variant-ligatures: normal; font-variant-caps: normal; font-weight: 400; letter-spacing: 0.112px; word-spacing: -0.35px; background-color: rgb(255, 254, 250);\">&nbsp; -&nbsp;주소 : 1026 Budapest, G&aacute;bor &aacute;ron u. 74-78/a</span><br style=\"letter-spacing: -0.025em; word-spacing: -0.35px; color: rgb(51, 51, 51); font-family: NBG, Arial, sans-serif; font-size: 14px; background-color: rgb(255, 254, 250);\">\n <span style=\"color: rgb(0, 0, 0); font-family: NBG, Arial, sans-serif; font-size: 14px; font-style: normal; font-variant-ligatures: normal; font-variant-caps: normal; font-weight: 400; letter-spacing: 0.112px; word-spacing: -0.35px; background-color: rgb(255, 254, 250);\">&nbsp; -&nbsp;전화 : (+36 1) 392 0505</span><br style=\"letter-spacing: -0.025em; word-spacing: -0.35px; color: rgb(51, 51, 51); font-family: NBG, Arial, sans-serif; font-size: 14px; background-color: rgb(255, 254, 250);\">\n <span style=\"color: rgb(0, 0, 0); font-family: NBG, Arial, sans-serif; font-size: 14px; font-style: normal; font-variant-ligatures: normal; font-variant-caps: normal; font-weight: 400; letter-spacing: 0.112px; word-spacing: -0.35px; background-color: rgb(255, 254, 250);\">&nbsp; -&nbsp;근무시간 : (월-금) 08.00-20.00 / (토) 09.00-14.00</span></p>\n<p class=\"a\" style=\"margin: 0px; padding: 0px; border: 0px; font-style: normal; font-variant-ligatures: normal; font-variant-caps: normal; font-variant-numeric: inherit; font-variant-east-asian: inherit; font-variant-alternates: inherit; font-variant-position: inherit; font-variant-emoji: inherit; font-weight: 400; font-stretch: inherit; font-size: 16px; line-height: inherit; font-family: 'Open sans', 'Noto sans', sans-serif, '맑은 고딕'; font-optical-sizing: inherit; font-size-adjust: inherit; font-kerning: inherit; font-feature-settings: inherit; font-variation-settings: inherit; box-sizing: border-box; color: rgb(0, 0, 0); letter-spacing: -0.08px; orphans: 2; text-align: left; text-indent: 0px; text-transform: none; widows: 2; word-spacing: 0px; -webkit-text-stroke-width: 0px; white-space: normal; text-decoration-thickness: initial; text-decoration-style: initial; text-decoration-color: initial;\"><span style=\"margin: 0px; padding: 0px; border: 0px; font-style: inherit; font-variant: inherit; font-weight: inherit; font-stretch: inherit; font-size: 12pt; line-height: inherit; font-family: '맑은 고딕'; font-optical-sizing: inherit; font-size-adjust: inherit; font-kerning: inherit; font-feature-settings: inherit; font-variation-settings: inherit; box-sizing: border-box; letter-spacing: -0.05em; color: rgb(0, 0, 0);\"><br></span></p>\n<p style=\"margin: 0px; padding: 0px; border: 0px; font-style: normal; font-variant-ligatures: normal; font-variant-caps: normal; font-variant-numeric: inherit; font-variant-east-asian: inherit; font-variant-alternates: inherit; font-variant-position: inherit; font-variant-emoji: inherit; font-weight: 400; font-stretch: inherit; font-size: 16px; line-height: inherit; font-family: 'Open sans', 'Noto sans', sans-serif, '맑은 고딕'; font-optical-sizing: inherit; font-size-adjust: inherit; font-kerning: inherit; font-feature-settings: inherit; font-variation-settings: inherit; box-sizing: border-box; color: rgb(0, 0, 0); letter-spacing: -0.08px; orphans: 2; text-align: left; text-indent: 0px; text-transform: none; widows: 2; word-spacing: 0px; -webkit-text-stroke-width: 0px; white-space: normal; text-decoration-thickness: initial; text-decoration-style: initial; text-decoration-color: initial;\"><span style=\"background-color: rgb(255, 255, 255); color: rgb(0, 0, 0); font-family: '맑은 고딕'; font-size: 15px; font-style: normal; font-variant-ligatures: normal; font-variant-caps: normal; font-weight: 400; letter-spacing: -0.39px;\">※&nbsp;</span><span style=\"color: rgb(0, 0, 0); font-family: '맑은 고딕'; font-size: 16px; font-style: normal; font-variant-ligatures: normal; font-variant-caps: normal; font-weight: 400; letter-spacing: -0.4px;\">유의사항:<br></span></p>\n<p class=\"a\" style=\"font-style: normal; font-variant-ligatures: normal; font-variant-caps: normal; font-weight: 400;\"><span style=\"font-family: '맑은 고딕'; color: rgb(0, 0, 0);\">&nbsp;-&nbsp;</span><span style=\"color: rgb(0, 0, 0); font-family: '맑은 고딕'; font-size: 12pt; letter-spacing: -0.05em;\">헝가리에서</span><span style=\"color: rgb(0, 0, 0); font-family: '맑은 고딕'; font-size: 12pt; letter-spacing: -0.05em;\">&nbsp;</span><span style=\"color: rgb(0, 0, 0); font-family: '맑은 고딕'; font-size: 12pt; letter-spacing: -0.05em;\">병원</span><span style=\"color: rgb(0, 0, 0); font-family: '맑은 고딕'; font-size: 12pt; letter-spacing: -0.05em;\">&nbsp;</span><span style=\"color: rgb(0, 0, 0); font-family: '맑은 고딕'; font-size: 12pt; letter-spacing: -0.05em;\">이용</span><span style=\"color: rgb(0, 0, 0); font-family: '맑은 고딕'; font-size: 12pt; letter-spacing: -0.05em;\">&nbsp;</span><span style=\"color: rgb(0, 0, 0); font-family: '맑은 고딕'; font-size: 12pt; letter-spacing: -0.05em;\">시에는</span><span style=\"color: rgb(0, 0, 0); font-family: '맑은 고딕'; font-size: 12pt; letter-spacing: -0.05em;\">&nbsp;</span><span style=\"color: rgb(0, 0, 0); font-family: '맑은 고딕'; font-size: 12pt; letter-spacing: -0.05em;\">반드시</span><span style=\"color: rgb(0, 0, 0); font-family: '맑은 고딕'; font-size: 12pt; letter-spacing: -0.05em;\">&nbsp;</span><span style=\"color: rgb(0, 0, 0); font-family: '맑은 고딕'; font-size: 12pt; letter-spacing: -0.05em;\">여권을</span><span style=\"color: rgb(0, 0, 0); font-family: '맑은 고딕'; font-size: 12pt; letter-spacing: -0.05em;\">&nbsp;</span><span style=\"color: rgb(0, 0, 0); font-family: '맑은 고딕'; font-size: 12pt; letter-spacing: -0.05em;\">지참해</span><span style=\"color: rgb(0, 0, 0); font-family: '맑은 고딕'; font-size: 12pt; letter-spacing: -0.05em;\">&nbsp;</span><span style=\"color: rgb(0, 0, 0); font-family: '맑은 고딕'; font-size: 12pt; letter-spacing: -0.05em;\">주시기</span><span style=\"color: rgb(0, 0, 0); font-family: '맑은 고딕'; font-size: 12pt; letter-spacing: -0.05em;\">&nbsp;</span><span style=\"color: rgb(0, 0, 0); font-family: '맑은 고딕'; font-size: 12pt; letter-spacing: -0.05em;\">바랍니다.&nbsp;</span></p>\n<p class=\"a\" style=\"font-style: normal; font-variant-ligatures: normal; font-variant-caps: normal; font-weight: 400; font-size: 16px; font-family: 'Open sans', 'Noto sans', 'sans-serif', '맑은 고딕'; color: rgb(0, 0, 0); letter-spacing: -0.08px;\"><span style=\"font-family: '맑은 고딕'; font-size: 16px; font-style: normal; font-variant-ligatures: normal; font-variant-caps: normal; font-weight: 400; letter-spacing: -0.4px; color: rgb(0, 0, 0);\">&nbsp;-&nbsp;</span><span lang=\"EN-US\" style=\"font-size: 12pt; font-style: normal; font-variant-ligatures: normal; font-variant-caps: normal; font-weight: 400; font-family: '맑은 고딕'; letter-spacing: -0.05em; text-indent: -63.3333px; color: rgb(0, 0, 0);\">응급실을 직접 방문하는 경우에도 대기 환자에 따라 5-6시간 이상 대기해야하는&nbsp;</span><span style=\"font-size: 12pt; font-style: normal; font-variant-ligatures: normal; font-variant-caps: normal; font-weight: 400; font-family: '맑은 고딕'; letter-spacing: -0.05em; text-indent: -63.3333px; color: rgb(0, 0, 0);\">상황이</span><span style=\"font-size: 12pt; font-style: normal; font-variant-ligatures: normal; font-variant-caps: normal; font-weight: 400; font-family: '맑은 고딕'; letter-spacing: -0.05em; text-indent: -63.3333px; color: rgb(0, 0, 0);\">&nbsp;빈번히&nbsp;</span><span style=\"font-size: 12pt; font-style: normal; font-variant-ligatures: normal; font-variant-caps: normal; font-weight: 400; font-family: '맑은 고딕'; letter-spacing: -0.05em; text-indent: -63.3333px; color: rgb(0, 0, 0);\">발생합니다.</span><span style=\"font-size: 12pt; font-style: normal; font-variant-ligatures: normal; font-variant-caps: normal; font-weight: 400; font-family: '맑은 고딕'; letter-spacing: -0.05em; text-indent: -63.3333px; color: rgb(0, 0, 0);\">&nbsp;&nbsp;</span></p>\n<p class=\"a\" style=\"font-style: normal; font-variant-ligatures: normal; font-variant-caps: normal; font-weight: 400; font-size: 16px; font-family: 'Open sans', 'Noto sans', 'sans-serif', '맑은 고딕'; color: rgb(0, 0, 0); letter-spacing: -0.08px;\"><span style=\"font-family: '맑은 고딕'; font-size: 16px; font-style: normal; font-variant-ligatures: normal; font-variant-caps: normal; font-weight: 400; letter-spacing: -0.4px; color: rgb(0, 0, 0);\">&nbsp;-&nbsp;</span><span style=\"font-size: 12pt; font-style: normal; font-variant-ligatures: normal; font-variant-caps: normal; font-weight: 400; font-family: '맑은 고딕'; letter-spacing: -0.05em; text-indent: -63.3333px; color: rgb(0, 0, 0);\">일반 병원의 경우&nbsp;</span><span style=\"font-size: 12pt; font-style: normal; font-variant-ligatures: normal; font-variant-caps: normal; font-weight: 400; font-family: '맑은 고딕'; letter-spacing: -0.05em; text-indent: -63.3333px; color: rgb(0, 0, 0);\">예약을</span><span style=\"font-size: 12pt; font-style: normal; font-variant-ligatures: normal; font-variant-caps: normal; font-weight: 400; font-family: '맑은 고딕'; letter-spacing: -0.05em; text-indent: -63.3333px; color: rgb(0, 0, 0);\">&nbsp;하신</span><span style=\"font-size: 12pt; font-style: normal; font-variant-ligatures: normal; font-variant-caps: normal; font-weight: 400; font-family: '맑은 고딕'; letter-spacing: -0.05em; text-indent: -63.3333px; color: rgb(0, 0, 0);\">&nbsp;</span><span style=\"font-size: 12pt; font-style: normal; font-variant-ligatures: normal; font-variant-caps: normal; font-weight: 400; font-family: '맑은 고딕'; letter-spacing: -0.05em; text-indent: -63.3333px; color: rgb(0, 0, 0);\">후</span><span style=\"font-size: 12pt; font-style: normal; font-variant-ligatures: normal; font-variant-caps: normal; font-weight: 400; font-family: '맑은 고딕'; letter-spacing: -0.05em; text-indent: -63.3333px; color: rgb(0, 0, 0);\">&nbsp;</span><span style=\"font-size: 12pt; font-style: normal; font-variant-ligatures: normal; font-variant-caps: normal; font-weight: 400; font-family: '맑은 고딕'; letter-spacing: -0.05em; text-indent: -63.3333px; color: rgb(0, 0, 0);\">방문</span><span style=\"font-size: 12pt; font-style: normal; font-variant-ligatures: normal; font-variant-caps: normal; font-weight: 400; font-family: '맑은 고딕'; letter-spacing: -0.05em; text-indent: -63.3333px; color: rgb(0, 0, 0);\">하</span><span style=\"font-size: 12pt; font-style: normal; font-variant-ligatures: normal; font-variant-caps: normal; font-weight: 400; font-family: '맑은 고딕'; letter-spacing: -0.05em; text-indent: -63.3333px; color: rgb(0, 0, 0);\">시기</span><span style=\"font-size: 12pt; font-style: normal; font-variant-ligatures: normal; font-variant-caps: normal; font-weight: 400; font-family: '맑은 고딕'; letter-spacing: -0.05em; text-indent: -63.3333px; color: rgb(0, 0, 0);\">&nbsp;</span><span style=\"font-size: 12pt; font-style: normal; font-variant-ligatures: normal; font-variant-caps: normal; font-weight: 400; font-family: '맑은 고딕'; letter-spacing: -0.05em; text-indent: -63.3333px; color: rgb(0, 0, 0);\">바랍니다. 예약없이 방문시 진료가 불가능할 수 있습니다.&nbsp;&nbsp;</span></p>\n<p class=\"a\" style=\"font-style: normal; font-variant-ligatures: normal; font-variant-caps: normal; font-weight: 400; font-size: 16px; font-family: 'Open sans', 'Noto sans', 'sans-serif', '맑은 고딕'; color: rgb(0, 0, 0); letter-spacing: -0.08px;\"><span style=\"font-family: '맑은 고딕'; font-size: 16px; font-style: normal; font-variant-ligatures: normal; font-variant-caps: normal; font-weight: 400; letter-spacing: -0.4px; color: rgb(0, 0, 0);\">&nbsp;-&nbsp;</span><span style=\"font-size: 12pt; font-style: normal; font-variant-ligatures: normal; font-variant-caps: normal; font-weight: bold; font-family: '맑은 고딕'; letter-spacing: -0.05em; text-decoration-line: underline; text-indent: -61.7333px; color: rgb(0, 0, 0);\">응</span><span style=\"font-size: 12pt; font-style: normal; font-variant-ligatures: normal; font-variant-caps: normal; font-weight: bold; font-family: '맑은 고딕'; letter-spacing: -0.05em; text-decoration-line: underline; text-indent: -61.7333px; color: rgb(0, 0, 0);\">급</span><span style=\"font-size: 12pt; font-style: normal; font-variant-ligatures: normal; font-variant-caps: normal; font-weight: bold; font-family: '맑은 고딕'; letter-spacing: -0.05em; text-decoration-line: underline; text-indent: -61.7333px; color: rgb(0, 0, 0);\">&nbsp;</span><span style=\"font-size: 12pt; font-style: normal; font-variant-ligatures: normal; font-variant-caps: normal; font-weight: bold; font-family: '맑은 고딕'; letter-spacing: -0.05em; text-decoration-line: underline; text-indent: -61.7333px; color: rgb(0, 0, 0);\">상황</span><span style=\"font-size: 12pt; font-style: normal; font-variant-ligatures: normal; font-variant-caps: normal; font-weight: bold; font-family: '맑은 고딕'; letter-spacing: -0.05em; text-decoration-line: underline; text-indent: -61.7333px; color: rgb(0, 0, 0);\">&nbsp;</span><span style=\"font-size: 12pt; font-style: normal; font-variant-ligatures: normal; font-variant-caps: normal; font-weight: bold; font-family: '맑은 고딕'; letter-spacing: -0.05em; text-decoration-line: underline; text-indent: -61.7333px; color: rgb(0, 0, 0);\">발생시에는</span><span style=\"font-size: 12pt; font-style: normal; font-variant-ligatures: normal; font-variant-caps: normal; font-weight: bold; font-family: '맑은 고딕'; letter-spacing: -0.05em; text-decoration-line: underline; text-indent: -61.7333px; color: rgb(0, 0, 0);\">&nbsp;</span><span style=\"font-size: 12pt; font-style: normal; font-variant-ligatures: normal; font-variant-caps: normal; font-weight: bold; font-family: '맑은 고딕'; letter-spacing: -0.05em; text-decoration-line: underline; text-indent: -61.7333px; color: rgb(0, 0, 0);\">반드시</span><span style=\"font-size: 12pt; font-style: normal; font-variant-ligatures: normal; font-variant-caps: normal; font-weight: bold; font-family: '맑은 고딕'; letter-spacing: -0.05em; text-decoration-line: underline; text-indent: -61.7333px; color: rgb(0, 0, 0);\">&nbsp;</span><span lang=\"EN-US\" style=\"font-size: 12pt; font-style: normal; font-variant-ligatures: normal; font-variant-caps: normal; font-weight: bold; font-family: '맑은 고딕'; letter-spacing: -0.05em; text-decoration-line: underline; text-indent: -61.7333px; color: rgb(0, 0, 0);\">112(</span><span style=\"font-size: 12pt; font-style: normal; font-variant-ligatures: normal; font-variant-caps: normal; font-weight: bold; font-family: '맑은 고딕'; letter-spacing: -0.05em; text-decoration-line: underline; text-indent: -61.7333px; color: rgb(0, 0, 0);\">긴급서비스</span><span lang=\"EN-US\" style=\"font-size: 12pt; font-style: normal; font-variant-ligatures: normal; font-variant-caps: normal; font-weight: bold; font-family: '맑은 고딕'; letter-spacing: -0.05em; text-decoration-line: underline; text-indent: -61.7333px; color: rgb(0, 0, 0);\">)&nbsp;</span><span style=\"font-size: 12pt; font-style: normal; font-variant-ligatures: normal; font-variant-caps: normal; font-weight: bold; font-family: '맑은 고딕'; letter-spacing: -0.05em; text-decoration-line: underline; text-indent: -61.7333px; color: rgb(0, 0, 0);\">또는</span><span style=\"font-size: 12pt; font-style: normal; font-variant-ligatures: normal; font-variant-caps: normal; font-weight: bold; font-family: '맑은 고딕'; letter-spacing: -0.05em; text-decoration-line: underline; text-indent: -61.7333px; color: rgb(0, 0, 0);\">&nbsp;</span><span lang=\"EN-US\" style=\"font-size: 12pt; font-style: normal; font-variant-ligatures: normal; font-variant-caps: normal; font-weight: bold; font-family: '맑은 고딕'; letter-spacing: -0.05em; text-decoration-line: underline; text-indent: -61.7333px; color: rgb(0, 0, 0);\">104(</span><span style=\"font-size: 12pt; font-style: normal; font-variant-ligatures: normal; font-variant-caps: normal; font-weight: bold; font-family: '맑은 고딕'; letter-spacing: -0.05em; text-decoration-line: underline; text-indent: -61.7333px; color: rgb(0, 0, 0);\">앰뷸런스</span><span lang=\"EN-US\" style=\"font-size: 12pt; font-style: normal; font-variant-ligatures: normal; font-variant-caps: normal; font-weight: bold; font-family: '맑은 고딕'; letter-spacing: -0.05em; text-decoration-line: underline; text-indent: -61.7333px; color: rgb(0, 0, 0);\">)</span><span style=\"font-size: 12pt; font-style: normal; font-variant-ligatures: normal; font-variant-caps: normal; font-weight: bold; font-family: '맑은 고딕'; letter-spacing: -0.05em; text-decoration-line: underline; text-indent: -61.7333px; color: rgb(0, 0, 0);\">에</span><span style=\"font-size: 12pt; font-style: normal; font-variant-ligatures: normal; font-variant-caps: normal; font-weight: bold; font-family: '맑은 고딕'; letter-spacing: -0.05em; text-decoration-line: underline; text-indent: -61.7333px; color: rgb(0, 0, 0);\">&nbsp;</span><span style=\"font-size: 12pt; font-style: normal; font-variant-ligatures: normal; font-variant-caps: normal; font-weight: bold; font-family: '맑은 고딕'; letter-spacing: -0.05em; text-decoration-line: underline; text-indent: -61.7333px; color: rgb(0, 0, 0);\">연락해</span><span style=\"font-size: 12pt; font-style: normal; font-variant-ligatures: normal; font-variant-caps: normal; font-weight: bold; font-family: '맑은 고딕'; letter-spacing: -0.05em; text-decoration-line: underline; text-indent: -61.7333px; color: rgb(0, 0, 0);\">&nbsp;</span><span style=\"font-size: 12pt; font-style: normal; font-variant-ligatures: normal; font-variant-caps: normal; font-weight: bold; font-family: '맑은 고딕'; letter-spacing: -0.05em; text-decoration-line: underline; text-indent: -61.7333px; color: rgb(0, 0, 0);\">주시기</span><span style=\"font-size: 12pt; font-style: normal; font-variant-ligatures: normal; font-variant-caps: normal; font-weight: bold; font-family: '맑은 고딕'; letter-spacing: -0.05em; text-decoration-line: underline; text-indent: -61.7333px; color: rgb(0, 0, 0);\">&nbsp;</span><span style=\"font-size: 12pt; font-style: normal; font-variant-ligatures: normal; font-variant-caps: normal; font-weight: bold; font-family: '맑은 고딕'; letter-spacing: -0.05em; text-decoration-line: underline; text-indent: -61.7333px; color: rgb(0, 0, 0);\">바랍니다</span><span lang=\"EN-US\" style=\"font-size: 12pt; font-style: normal; font-variant-ligatures: normal; font-variant-caps: normal; font-weight: bold; font-family: '맑은 고딕'; letter-spacing: -0.05em; text-decoration-line: underline; text-indent: -61.7333px; color: rgb(0, 0, 0);\">.</span><span style=\"font-family: '맑은 고딕'; font-size: 12pt; letter-spacing: -0.05em; text-indent: -61.7333px; color: rgb(0, 0, 0);\">&nbsp;</span></p>\n<p class=\"a\" style=\"font-style: normal; font-variant-liga",
  "notice_url": "https://www.0404.go.kr/ntnSafetyInfo/list",
  "culture_ai": {
    "etiquette": "헝가리에서는 식당에서 식사할 때 팁을 주는 것이 관례이며, 보통 결제 금액의 10% 정도를 현금으로 직접 건네는 것이 좋습니다. 대중교통 이용 시에는 반드시 탑승 전 티켓을 개표해야 하며, 실내나 공공장소에서 크게 소리 내어 말하는 것은 예의에 어긋난다고 생각합니다. 술자리에서 잔을 부딪치며 건배할 때는 상대방의 눈을 맞추는 것이 중요하며, 맥주잔끼리 부딪치는 것은 피하는 것이 좋습니다.",
    "business_tip": "비즈니스 미팅에서는 정중하고 격식을 갖춘 복장이 필수적이며, 첫 만남에서는 악수와 함께 명함을 교환하는 것이 일반적입니다. 약속 시간에 늦지 않는 것을 매우 중요하게 생각하므로 시간 엄수는 비즈니스의 신뢰도를 결정하는 핵심 요소입니다.",
    "phrases": [
      "안녕하세요 - 요우 너폿 (Jó napot)",
      "감사합니다 - 쾨쇠뇸 (Köszönöm)",
      "부탁합니다/부디 - 케렘 (Kérem)",
      "네/아니요 - 이겐/넴 (Igen/Nem)",
      "얼마인가요? - 멘니베 케룰? (Mennyibe kerül?)"
    ]
  }
}