{
  "iso_code": "RUS",
  "country_kr": "러시아",
  "country_en": "Russia",
  "flag_image": "public/images/RUS.png",
  "travel_alert": {
    "level": "여행금지",
    "national_level": "없음",
    "partial_level": "여행금지",
    "regions": [
      {
        "level": "철수권고",
        "area": "북카프카즈 지역(체첸/다게스탄/세베로오세티아/카바르디노발카르/잉귀시/까라차예보체르케스카야/아디게이) 및 우크라이나 접경지역(4단계 제외 로스토프, 벨고로드, 보로네시, 브랸스크 주 및 오룔 주 일부(샤블리키노, 드미트롭스크, 사스코보, 크로믜, 트로스나 5개 지역))",
        "partial": true
      },
      {
        "level": "여행금지",
        "area": "우크라이나 접경지역(쿠르스크주 전체 및 로스토프·벨고로드·보로네시·브랸스크 지역 내 우크라이나 국경에서 30km 구간)",
        "partial": true
      }
    ]
  },
  "accident_info_html": "",
  "local_contact_html": "<h3> 대사관 연락처</h3>\n<p>[주러시아대사관]<br>\n ㅇ     주소 : St. Plyushchikha 56 bldg 1, Moscow<br>\n ㅇ     이메일 : <a href=\"mailto:embru@mofa.go.kr\" target=\"_blank\" rel=\"noopener\">embru@mofa.go.kr</a><br>\n ㅇ     대표번호(근무시간 중) : +(7) 495-783-2727<br>\n ㅇ     긴급연락처(사건사고 등 긴급상황 발생 시, 24시간) : +(7) 495-783-2727<br>\n <br>\n [주블라디보스톡총영사관]<br>\n ㅇ     주소 : Consulate General of the Republic of Korea Pologaya St. 19 Vladivostok 690091 Russia<br>\n ㅇ     이메일 : <a href=\"mailto:korvl@mofa.go.kr\" target=\"_blank\" rel=\"noopener\">korvl@mofa.go.kr</a><br>\n ㅇ     대표번호(근무시간 중) : +(7) 423-240-2222<br>\n ㅇ     긴급연락처(사건사고 등 긴급상황 발생 시, 24시간) : +(7) 914-072-8347<br>\n <br>\n [주상트페테르부르크총영사관]<br>\n ㅇ     주소 : St. Nekrasova 32-A, St. Petersburg,191014, Russia<br>\n ㅇ     이메일 : <a href=\"mailto:korpb@mofa.go.kr\" target=\"_blank\" rel=\"noopener\">korpb@mofa.go.kr</a><br>\n ㅇ     대표번호(근무시간 중) : +(7) 812-448-1909<br>\n ㅇ     긴급연락처(사건사고 등 긴급상황 발생 시, 24시간) : +(7) 905-255-5496<br>\n <br>\n [주이르쿠츠크총영사관]<br>\n ㅇ     주소 : Gagarin Blvd. 44, Irkutsk, Russia<br>\n ㅇ     이메일 : <a href=\"mailto:irkutsk@mofa.go.kr\" target=\"_blank\" rel=\"noopener\">irkutsk@mofa.go.kr</a><br>\n ㅇ     대표번호(근무시간 중) : +(7) 3952-250-301<br>\n ㅇ     긴급연락처(사건사고 등 긴급상황 발생 시, 24시간) : +(7) 964-650-9403<br>\n <br>\n [주유즈노사할린스크출장소]<br>\n ㅇ     주소 : 283 B, Lenin St., Yuzhno-Sakhalinsk, Russia<br>\n ㅇ     대표번호(근무시간 중) : +(7) 4242-462-430<br>\n ㅇ     긴급연락처(사건사고 발생 시 영사콜센터) : +82-2-3210-0404<br>\n<br>\n<br></p>\n<h3> 주재국 신고</h3>\n<p>[모스크바]<br>\n ㅇ     통합긴급안내 : 112 (안내멘트(노어,영어) 후 상황별 안내)<br>\n ㅇ     화재(구조) : 101<br>\n ㅇ     경찰 : 102<br>\n ㅇ     구급차 : 103<br>\n ㅇ     가스서비스 : 104<br>\n ㅇ     코로나19 지원(구급차 등) 핫라인 : 122<br>\n ㅇ     종합병원(보트킨) : 8(499)490-03-03, 8(800)600-31-41<br>\n ㅇ     택 시 : 8(495)999-99-99, 8(495)505-55-55<br>\n ㅇ     분실신고(지하철) : 8(495)622-20-85, 8(495)539-54-54<br>\n <br>\n [블라디보스톡]<br>\n ㅇ     통합긴급안내 : 112 (1차연결 후 상황별 안내)<br>\n ㅇ     화재(구조) : 101<br>\n ㅇ     경찰 : 102<br>\n ㅇ     구급차 : 103<br>\n ㅇ     가스서비스 : 104<br>\n ㅇ     종합병원 응급실 : +7-423-279-0790&gt;<br>\n ㅇ     택시 : +7-423-288-8888<br>\n <br>\n [상트페테르부르크]<br>\n ㅇ     안전신고센터 : 112 (유심 없이도 전화 가능)<br>\n ㅇ     화 재 : 01<br>\n ㅇ     경 찰 : 02<br>\n ㅇ     구급차 : 03<br>\n ㅇ     가스 서비스 : 04<br>\n ㅇ     종합병원(마린스카야): +7-812-605-03-03<br>\n ㅇ     택시 : Yandex +7-812-366-66-66, Vezet +7-812-318-03-18<br>\n ㅇ     분실신고(지하철) : +7-812-278-36-90<br>\n <br>\n [이르쿠츠크]<br>\n ㅇ     화재 : 01; 112, 또는 8(3952)25-79-01<br>\n ㅇ     경찰 : 02, 또는 8(3952)21-65-11<br>\n ㅇ     구급차 : 03, 또는 8(3952)29-24-36<br>\n ㅇ     가스서비스 : 04, 또는 8(3952)29-40-41<br>\n ㅇ     종합병원 응급실 : 8(3952)46-53-71, 8(3952)46-53-76, 8(3952)46-53-72<br>\n ㅇ     택시 : 8(3952)500700</p>\n<p><br></p>\n<p>[유즈노사할린스크]<br>\n ㅇ 화재 : 101,112<br>\n ㅇ 경찰 : 112<br>\n ㅇ 구급차 : 103<br>\n ㅇ 가스서비스 : 104<br>\n ㅇ 종합병원 응급실 : +7-4242-76-06-30<br>\n<br></p>\n<h3> 관광통역 서비스</h3>\n<p>ㅇ     러시아에는 관광, 통역을 해주는 공공 전화 서비스는 현재까지 없습니다. 따라서 아래 사이트 및 현지 여행사, 센터 등을 통해 관련 문의(대부분 영어 통역)를 해야 합니다.<br>\n ㅇ     유용한 사이트 : <a href=\"http://expat.ru/\" target=\"_blank\" rel=\"noopener\">http://expat.ru</a>(Survivalguide)<br>\n ㅇ     한국관광공사 모스크바 지사 : 8(495)989-46-78<br>\n<br></p>\n<h3> 의료기관 연락처</h3>\n<p>[모스크바     내 종합병원]<br>\n ㅇ     EMC(European Medical Center) : 영어 진료 가능, 친절한 보조원의 개별 상담 및 관리가 장점, 현지화(루블)와 카드 사용만 가능, 각종 예방접종 실시, 코로나19 검사     가능<br></p>\n<p>- 홈페이지 : <a href=\"http://www.emcmos.ru/\" target=\"_blank\" rel=\"noopener\">http://www.emcmos.ru</a><br>\n - 주소 : St.shchepkina 35<br>- 전화번호 : 8(495)933-66-55</p>\n<p><br>\nㅇ     International Clinic MEDSI : 가족단위 진료시스템과 소아ㆍ여성 진료센터, 구강센터, 외과, 산부인과 등이 유명, 현지화(루블) 및 카드 사용만 가능, 각종 예방접종 실시, 코로나19 검사     가능<br></p>\n<p>- 홈페이지 : <a href=\"http://medsi.ru/\" target=\"_blank\" rel=\"noopener\">http://medsi.ru</a><br>\n - 주소 : Prospekt Mira 26, bld 6<br>- 전화번호 : 8(495)023-60-68</p>\n<p><br>\nㅇ     GMS (Global Medical System) : 소아과, 내과, 산부인과, 피부과 등 진료, 현지화(루블)와 카드 사용만 가능, 각종 예방접종 실시, 코로나19 검사 가능<br></p>\n<p>- 홈페이지 : <a href=\"http://www.gmsclinic.ru/\" target=\"_blank\" rel=\"noopener\">http://www.gmsclinic.ru</a><br>\n - 주소 : Ul. 2-ya Yamskaya, 9<br>- 전화번호 : +7 (495)781-55-77</p>\n<p><br>\n[블라디보스톡내     종합병원]<br>\n ㅇ     팔크국제병원<br>\n 주소     : Zaporozhskaya, 77<br>\n 전화     : +7-423-279-0790<br>\n ㅇ     시립2호 종합병원<br>\n 주소     : Russkaya, 57<br>\n 전화     : +7-423-232-6346<br>\n <br>\n [상트페테르부르크     종합병원]<br>\n ㅇ     Euromed : 영어 사용 가능<br></p>\n<p>- 홈페이지 : <a href=\"https://euromed.clinic/doctors/\" target=\"_blank\" rel=\"noopener\">https://euromed.clinic/doctors/</a><br>\n - 주소 : Suvorovskiy Prospekt, 60<br>- 전화번호 : + 7-812-327-03-01</p>\n<p><br>\nㅇ     Scandinavia : 앱을 통한 예약 및 영어 사용 가능<br></p>\n<p>- 홈페이지 : <a href=\"https://www.avaclinic.ru/en/\" target=\"_blank\" rel=\"noopener\">https://www.avaclinic.ru/en/</a><br>\n - 주소 : 133/1 Savushkina Street<br>- 전화번호 :+7-812-600-78-11</p>\n<p><br>\n[이르쿠츠크     내 종합병원]<br>\n ㅇ     이르쿠츠크시 1 병원<br></p>\n<p>- 홈페이지 : <a href=\"http://www.irgkb1.ru/\" target=\"_blank\" rel=\"noopener\">http://www.irgkb1.ru/</a><br>- 전화 : 8(3952)703726</p>\n<p><br>\nㅇ     이르쿠츠크 국립병원<br></p>\n<p>- 주소 : Jubilejnj District 100<br>- 전화 : 8(3952) 407894</p>\n<p><br></p>\n<p><br>\n[유즈노사할린스크내     종합병원]<br>\n ㅇ     유즈노사할린스크 주립병원</p>\n<p>- 홈페이지 : <a href=\"http://sakh-hospital.sakhalin.gov.ru/\" target=\"_blank\" rel=\"noopener\">http://</a>sakhokb.gosuslugi.ru<br>\n- 주소 : Prospect Mira, 430<br>- 대표전화 : +7 (4242) 49-73-62</p>\n<p>- 접수과 : +7 (4242 49-73-61</p>\n<p><br></p>\n<p>ㅇ 유즈노사할린스크 시립병원</p>\n<p>- 홈페이지 : <a href=\"http://sakh-hospital.sakhalin.gov.ru/\" target=\"_blank\" rel=\"noopener\">http://</a>sakhgb.sakhalin.gov.ru<br>- 주소 : Ankudinov Bulvar, 1A </p>\n<p>- 대표전화 : +7 (4242) 76-03-46</p>\n<p><br></p>\n<p>ㅇ 유즈노사할린스크 시립병원(정형외과 응급실)</p>\n<p>- 홈페이지 : <a href=\"http://sakh-hospital.sakhalin.gov.ru/\" target=\"_blank\" rel=\"noopener\">http://</a>sakhgb.sakhalin.gov.ru<br>\n- 주소 : Prospect Mira, 56A/3</p>\n<p>- 대표전화 : &lt;span style=&quot;font-style: norma",
  "notice_url": "https://www.0404.go.kr/ntnSafetyInfo/list",
  "culture_ai": {
    "etiquette": "💡 **러시아 현지 문화 및 예절**\n* **식당 및 대중교통**\n    * 식당에서 **팁 문화**는 선택사항이나 총액의 5~10% 권장\n    * 대중교통 이용 시 노약자에게 **좌석 양보**는 필수 예절\n* **방문 및 대인 관계**\n    * 지인 집 방문 시 **꽃은 홀수**로 준비 (짝수는 장례식용)\n    * 실내 입장 시 **외투 탈의** 후 보관소 이용 필수",
    "local_laws": "🚨 **필수 준수 법률 및 주의사항**\n* **신분증 및 체류**\n    * **여권 원본** 및 **입국신고서(Migration Card)** 상시 휴대 필수\n    * 무단 검문 시 불응은 **강제 구금** 및 **벌금형** 대상\n* **공공장소 행위**\n    * 거리 내 **음주 및 흡연** 엄격히 금지 (지정 구역 외)\n    * 허가 없는 **공공시설 촬영** 및 반정부적 언행 시 **처벌 및 추방** 위험\n* **마약 및 약물**\n    * 관련 약물 소지 적발 시 **최소 10년 이상 징역** 등 강력 처벌",
    "phrases": [
      "안녕하세요 - 즈드랏스부이쩨(Здравствуйте)",
      "감사합니다 - 스빠씨바(Спасибо)",
      "죄송합니다/실례합니다 - 이즈비니쩨(Извините)",
      "얼마인가요? - 스꼴까 스또잇?(Сколько стоит?)",
      "도와주세요 - 빠모기쩨(Помогите)"
    ]
  }
}